unify_live_telegram_integration_api_client/__init__.py
unify_live_telegram_integration_api_client/api/__init__.py
unify_live_telegram_integration_api_client/api/root/__init__.py
unify_live_telegram_integration_api_client/api/root/bot_webhook.py
unify_live_telegram_integration_api_client/api/root/register_bot.py
unify_live_telegram_integration_api_client/client.py
unify_live_telegram_integration_api_client/errors.py
unify_live_telegram_integration_api_client/models/__init__.py
unify_live_telegram_integration_api_client/models/bot_created_response.py
unify_live_telegram_integration_api_client/models/bot_webhook_update.py
unify_live_telegram_integration_api_client/models/http_validation_error.py
unify_live_telegram_integration_api_client/models/new_bot_request.py
unify_live_telegram_integration_api_client/models/validation_error.py
unify_live_telegram_integration_api_client/py.typed
unify_live_telegram_integration_api_client/types.py
unify_live_telegram_integration_api_client-0.0.7.dist-info/METADATA
unify_live_telegram_integration_api_client-0.0.7.dist-info/WHEEL
unify_live_telegram_integration_api_client-0.0.7.dist-info/RECORD
